README.rst
setup.py
AsyncScheduler.egg-info/PKG-INFO
AsyncScheduler.egg-info/SOURCES.txt
AsyncScheduler.egg-info/dependency_links.txt
AsyncScheduler.egg-info/top_level.txt
asyncscheduler/__init__.py
asyncscheduler/asyncscheduler.py
tests_unit/__init__.py
tests_unit/test_asyncscheduler.py