Metadata-Version: 1.2
Name: AsyncScheduler
Version: 0.1.0
Summary: A simpler asynchronous scheduler based on pythons sched.scheduler.
Home-page: https://gitlab.com/tgd1975/simple_asynchronous_scheduler/
Author: Tobias Gawron-Deutsch
Author-email: tobias@strix.at
License: MIT license
Keywords: sched scheduler
Platform: UNKNOWN
Classifier: Development Status :: 4 - Beta
Classifier: Environment :: Console
Classifier: Environment :: No Input/Output (Daemon)
Classifier: Intended Audience :: Developers
Classifier: Programming Language :: Python :: 3
Classifier: License :: OSI Approved :: MIT License
Requires-Python: >=3.5
